fragdenstaat_auth/__init__.py
fragdenstaat_auth/models.py
fragdenstaat_auth/provider.py
fragdenstaat_auth/tests.py
fragdenstaat_auth/urls.py
fragdenstaat_auth/views.py
django_allauth_fragdenstaat-0.0.2.dist-info/LICENSE
django_allauth_fragdenstaat-0.0.2.dist-info/METADATA
django_allauth_fragdenstaat-0.0.2.dist-info/WHEEL
django_allauth_fragdenstaat-0.0.2.dist-info/top_level.txt
django_allauth_fragdenstaat-0.0.2.dist-info/RECORD
